dns_benchmark/__init__.py
dns_benchmark/analysis.py
dns_benchmark/cli.py
dns_benchmark/core.py
dns_benchmark/exporters.py
dns_benchmark/utils/__init__.py
dns_benchmark/utils/messages.py
dns_benchmark_tool-0.2.9.dist-info/licenses/LICENSE
dns_benchmark_tool-0.2.9.dist-info/METADATA
dns_benchmark_tool-0.2.9.dist-info/WHEEL
dns_benchmark_tool-0.2.9.dist-info/entry_points.txt
dns_benchmark_tool-0.2.9.dist-info/top_level.txt
dns_benchmark_tool-0.2.9.dist-info/RECORD
