Metadata-Version: 2.4
Name: dns-benchmark-tool
Version: 0.2.9
Summary: Benchmark DNS resolvers across domains and record types with analytics and reports (CSV, Excel, PDF, JSON).
Author-email: Joseph Oseh Frank <frank@osehfrank.com>
License: MIT
Project-URL: Homepage, https://github.com/frankovo/dns-benchmark-tool
Project-URL: Documentation, https://github.com/frankovo/dns-benchmark-tool#readme
Project-URL: Source, https://github.com/frankovo/dns-benchmark-tool
Project-URL: Tracker, https://github.com/frankovo/dns-benchmark-tool/issues
Classifier: Development Status :: 5 - Production/Stable
Classifier: Intended Audience :: System Administrators
Classifier: Intended Audience :: Developers
Classifier: Topic :: Internet :: Name Service (DNS)
Classifier: Topic :: System :: Networking
Classifier: License :: OSI Approved :: MIT License
Classifier: Programming Language :: Python :: 3
Classifier: Programming Language :: Python :: 3.8
Classifier: Programming Language :: Python :: 3.9
Classifier: Programming Language :: Python :: 3.10
Classifier: Programming Language :: Python :: 3.11
Classifier: Programming Language :: Python :: 3.12
Requires-Python: >=3.9
License-File: LICENSE
Requires-Dist: dnspython<3.0,>=2.7
Requires-Dist: pandas<3.0,>=2.0
Requires-Dist: aiohttp<4.0,>=3.8
Requires-Dist: click<9.0,>=8.0
Requires-Dist: pyfiglet<2.0,>=1.0
Requires-Dist: colorama<1.0,>=0.4
Requires-Dist: Jinja2<4.0,>=3.1
Requires-Dist: weasyprint<67.0,>=66.0
Requires-Dist: openpyxl<4.0,>=3.1
Requires-Dist: pyyaml<7.0,>=6.0
Requires-Dist: tqdm<5.0,>=4.66
Requires-Dist: matplotlib<4.0,>=3.8
Requires-Dist: seaborn<0.14.0,>=0.13.2
Requires-Dist: pillow<12.0.0,>=11.0.0
Provides-Extra: dev
Requires-Dist: mypy<2.0,>=1.8; extra == "dev"
Requires-Dist: black<26.0,>=24.0; extra == "dev"
Requires-Dist: flake8<8.0,>=7.0; extra == "dev"
Requires-Dist: autopep8<3.0,>=2.0; extra == "dev"
Requires-Dist: pytest<9.0,>=8.0; extra == "dev"
Requires-Dist: coverage<8.0,>=7.6; extra == "dev"
Requires-Dist: isort<7.0,>=5.12; extra == "dev"
Requires-Dist: pytest-asyncio<2.0,>=0.23; extra == "dev"
Requires-Dist: commitizen<4.0,>=3.0; extra == "dev"
Dynamic: license-file
